orodha_keycloak/__init__.py
orodha_keycloak/connection.py
orodha_keycloak/exceptions.py
orodha_keycloak/connections/__init__.py
orodha_keycloak/connections/admin.py
orodha_keycloak/connections/client.py
orodha_keycloak-1.2.0.dist-info/METADATA
orodha_keycloak-1.2.0.dist-info/WHEEL
orodha_keycloak-1.2.0.dist-info/licenses/LICENSE
orodha_keycloak-1.2.0.dist-info/RECORD
