Metadata-Version: 2.1
Name: orodha-keycloak
Version: 1.2.0
Summary: A facade package used to perform required keycloak actions which will be made available throughout each Orodha service.
Author-email: Edison Stuart <edisonstaurt@gmail.com>
License-File: LICENSE
Classifier: License :: OSI Approved :: MIT License
Classifier: Operating System :: OS Independent
Classifier: Programming Language :: Python :: 3
Requires-Python: >=3.7
Requires-Dist: python-keycloak>=3.3.0
